{
   "Defaults":{
      "IndividualProperties":[
         {
            "Initial_Distribution":[
               0.4,
               0.3,
			   0.2,
               0.1
            ],
            "Property":"Place",
            "ScalingMatrix":{
               "Matrix":[

               ],
               "Route":"Contact"
            },
			"Transitions": [],
            "Transitions_None":[
               {
                  "Age_In_Years_Restriction":{
                  },
                  "Coverage":0.8,
                  "From":"High",
                  "Probability_Per_Timestep":1,
                  "Timestep_Restriction":{
                     "Start":150
                  },
                  "Timesteps_Until_Reversion":100,
                  "To":"Low",
                  "Type":"At_Timestep"
               }
            ],
            "Values":[
               "Cats",
               "Dogs",
			   "Birds",
               "None"
            ]
         }
      ],
      "IndividualProperties_FAKE":[
         {
            "Initial_Distribution":[
               0.05,
               0.2,
               0.4,
               0.2,
               0.15
            ],
            "Property":"Risk",
            "ScalingMatrix":{
               "Matrix":[
                  [
                     0.2,
                     0.6,
                     0.15,
                     0.05,
                     0.0
                  ],
                  [
                     0.4,
                     0.3,
                     0.2,
                     0.1,
                     0.0
                  ],
                  [
                     0.1,
                     0.3,
                     0.5,
                     0.1,
                     0.0
                  ],
                  [
                     0.0,
                     0.1,
                     0.4,
                     0.5,
                     0.0
                  ],
                  [
                     0.0,
                     0.0,
                     0.0,
                     0.0,
                     1.0
                  ]
               ],
               "Route":"Contact"
            },
            "Transitions":[
               {
                  "Age_In_Years_Restriction":{

                  },
                  "Coverage":0.8,
                  "From":"High",
                  "Probability_Per_Timestep":1,
                  "Timestep_Restriction":{
                     "Start":150
                  },
                  "Timesteps_Until_Reversion":100,
                  "To":"Low",
                  "Type":"At_Timestep"
               }
            ],
            "Values":[
               "Extreme",
               "High",
               "Medium",
               "Low",
               "None"
            ]
         }
      ]
   },
   "Metadata":{
      "Author":"cwiswell",
      "DateCreated":"Sun Sep 25 20:13:53 2011",
      "IdReference":"Fabricated",
      "NodeCount":9,
      "Resolution":30,
      "Tool":"demographics_to_overlay.py"
   },
   "Nodes":[
      {
         "NodeID":2695308866
      },
      {
         "NodeID":2695308867
      },
      {
         "NodeID":2695374403
      },
      {
         "NodeID":2695374402
      },
      {
         "NodeID":2695439939
      },
      {
         "NodeID":2695439938
      },
      {
         "NodeID":2695505475
      },
      {
         "NodeID":2695505474
      },
      {
         "NodeID":2682463747
      }
   ]
}